acp_calendar/__init__.py
acp_calendar/admin.py
acp_calendar/app_settings.py
acp_calendar/apps.py
acp_calendar/exceptions.py
acp_calendar/forms.py
acp_calendar/holiday_initial_data.json
acp_calendar/initial_data.py
acp_calendar/managers.py
acp_calendar/models.py
acp_calendar/urls.py
acp_calendar/utils.py
acp_calendar/views.py
acp_calendar/api/__init__.py
acp_calendar/api/serializers.py
acp_calendar/api/urls.py
acp_calendar/api/views.py
acp_calendar/management/__init__.py
acp_calendar/management/commands/__init__.py
acp_calendar/management/commands/acp_holidays.py
acp_calendar/migrations/0001_initial.py
acp_calendar/migrations/0002_load_holiday_type.py
acp_calendar/migrations/0003_acpholiday_fiscal_year.py
acp_calendar/migrations/__init__.py
acp_calendar/static/css/acp_calendar.css
acp_calendar/static/js/acp_calendar.js
acp_calendar/templates/base.html
acp_calendar/templates/acp_calendar/calculator.html
acp_calendar/templates/acp_calendar/fiscal_year_calendar.html
acp_calendar/templates/acp_calendar/home.html
acp_calendar/templates/acp_calendar/snippets/month_snippet.html
acp_calendar-1.6.0.dist-info/DESCRIPTION.rst
acp_calendar-1.6.0.dist-info/METADATA
acp_calendar-1.6.0.dist-info/RECORD
acp_calendar-1.6.0.dist-info/WHEEL
acp_calendar-1.6.0.dist-info/metadata.json
acp_calendar-1.6.0.dist-info/top_level.txt
