Metadata-Version: 2.0
Name: acp-calendar
Version: 1.6.0
Summary: Calendar and date management por the Panama Canal
Home-page: https://github.com/luiscberrocal/django-acp-calendar
Author: Luis Carlos Berrocal
Author-email: luis.berrocal.1942@gmail.com
License: BSD
Keywords: acp-calendar
Platform: UNKNOWN
Classifier: Development Status :: 5 - Production/Stable
Classifier: Framework :: Django
Classifier: Framework :: Django :: 1.9
Classifier: Framework :: Django :: 1.8
Classifier: Framework :: Django :: 1.10
Classifier: Framework :: Django :: 1.11
Classifier: Intended Audience :: Developers
Classifier: License :: OSI Approved :: BSD License
Classifier: Natural Language :: English
Classifier: Programming Language :: Python :: 3.4
Classifier: Programming Language :: Python :: 3.5
Classifier: Intended Audience :: Developers
Requires-Dist: djangorestframework (==3.6.4)
Requires-Dist: pytz (==2017.2)
